plato/client.py
plato/config.py
plato/models/__init__.py
plato/models/env.py
plato/models/task.py
plato/test/test_env.py
plato/test/test_run.py
plato_cli-0.1.33.dist-info/METADATA
plato_cli-0.1.33.dist-info/WHEEL
plato_cli-0.1.33.dist-info/RECORD
