Metadata-Version: 2.4
Name: plato-cli
Version: 0.1.33
Summary: Plato client
Author-email: Pranav Putta <pranav@plato.so>, Rob Farlow <rob@plato.so>
Requires-Python: >=3.8
Requires-Dist: aiohttp>=3.11.13
Requires-Dist: build>=1.2.2.post1
Requires-Dist: httpx>=0.28.1
Requires-Dist: pydantic-settings>=2.8.1
Requires-Dist: pydantic>=2.10.6
Requires-Dist: twine>=6.1.0
